lippu/__init__.py
lippu/__main__.py
lippu/api.py
lippu/cli.py
lippu/store.py
lippu/ticket_system_actions.py
lippu-2025.6.9.dist-info/licenses/LICENSE
lippu-2025.6.9.dist-info/METADATA
lippu-2025.6.9.dist-info/WHEEL
lippu-2025.6.9.dist-info/entry_points.txt
lippu-2025.6.9.dist-info/top_level.txt
lippu-2025.6.9.dist-info/RECORD
