Metadata-Version: 2.4
Name: lippu
Version: 2025.6.9
Summary: Ticket (Finnish: lippo) creator.
Author-email: Stefan Hagen <stefan@hagen.link>
Maintainer-email: Stefan Hagen <stefan@hagen.link>
License-Expression: MIT
Project-URL: Documentation, https://codes.dilettant.life/docs/lippu
Keywords: developer-tools,validation,verification
Classifier: Development Status :: 3 - Alpha
Classifier: Intended Audience :: Developers
Classifier: Programming Language :: Python :: 3.10
Classifier: Programming Language :: Python :: 3.11
Classifier: Programming Language :: Python :: 3.12
Classifier: Programming Language :: Python :: 3.13
Classifier: Programming Language :: Python :: 3.9
Requires-Python: >=3.9
License-File: LICENSE
Requires-Dist: atlassian-python-api>=3.41.3
Requires-Dist: jmespath>=1.0.1
Requires-Dist: wrapt>=1.16.0
Requires-Dist: tomli; python_version < "3.11"
Dynamic: license-file
